jarvis_conversationalist/__init__.py
jarvis_conversationalist/__main__.py
jarvis_conversationalist/assistant_history.py
jarvis_conversationalist/audio_identifier.py
jarvis_conversationalist/audio_listener.py
jarvis_conversationalist/audio_player.py
jarvis_conversationalist/audio_transcriber.py
jarvis_conversationalist/audio_vectordb.py
jarvis_conversationalist/config.py
jarvis_conversationalist/conversationalist.py
jarvis_conversationalist/logger_config.py
jarvis_conversationalist/openai_interface.py
jarvis_conversationalist/openai_utility_functions.py
jarvis_conversationalist/speaker_functions.py
jarvis_conversationalist/speaker_recognition.py
jarvis_conversationalist/streaming_response_audio.py
jarvis_conversationalist/text_speech.py
jarvis_conversationalist/audio_files/beeps.wav
jarvis_conversationalist/audio_files/booting.wav
jarvis_conversationalist/audio_files/connection_error.wav
jarvis_conversationalist/audio_files/go_on.wav
jarvis_conversationalist/audio_files/hmm.wav
jarvis_conversationalist/audio_files/listening.wav
jarvis_conversationalist/audio_files/major_error.wav
jarvis_conversationalist/audio_files/mic_error.wav
jarvis_conversationalist/audio_files/minor_error.wav
jarvis_conversationalist/audio_files/ready_in.wav
jarvis_conversationalist/audio_files/searching.wav
jarvis_conversationalist/audio_files/standard_response.wav
jarvis_conversationalist/audio_files/thinking.wav
jarvis_conversationalist/audio_files/tone_one.wav
jarvis_conversationalist/audio_files/tone_two.wav
jarvis_conversationalist/audio_files/yes.wav
jarvis_conversationalist/openai_functions/basic_tools.py
jarvis_conversationalist/openai_functions/functions.py
jarvis_conversationalist/openai_functions/google_tools.py
jarvis_conversationalist/openai_functions/internet_helper.py
jarvis_conversationalist/openai_functions/weather_functions.py
jarvis_conversationalist-0.5.0.dist-info/LICENSE
jarvis_conversationalist-0.5.0.dist-info/METADATA
jarvis_conversationalist-0.5.0.dist-info/WHEEL
jarvis_conversationalist-0.5.0.dist-info/entry_points.txt
jarvis_conversationalist-0.5.0.dist-info/top_level.txt
jarvis_conversationalist-0.5.0.dist-info/RECORD
