Metadata-Version: 2.1
Name: jarvis_conversationalist
Version: 0.5.0
Summary: A voice assistant for the command line
Author-email: Elias Weston-Farber <eweston4@jhu.edu>
Project-URL: url, https://github.com/elias-jhsph/jarvis-conversationalist
Classifier: Programming Language :: Python :: 3
Classifier: License :: OSI Approved :: GNU General Public License v3 (GPLv3)
Classifier: Operating System :: OS Independent
License-File: LICENSE
Requires-Dist: torch >2.0.0
Requires-Dist: openai ==1.13.3
Requires-Dist: openai-whisper
Requires-Dist: chromadb
Requires-Dist: soundfile ==0.12.1
Requires-Dist: sounddevice
Requires-Dist: pydub ==0.25.1
Requires-Dist: pyannote.audio ==3.1.0
Requires-Dist: faiss-cpu
Requires-Dist: gtts ==2.4.0
Requires-Dist: spacy ==3.7.2
Requires-Dist: beautifulsoup4 ==4.12.2
Requires-Dist: googlesearch-python ==1.2.3
Requires-Dist: tiktoken ==0.5.1
Requires-Dist: geocoder ==1.38.1
Requires-Dist: scrapy ==2.11.0
Requires-Dist: mycroft-mimic3-tts[all] ; sys_platform == "linux"
Requires-Dist: pysqlite3-binary ; sys_platform == "linux"
